MANIFEST.in
README.rst
requirements.txt
setup.py
version.txt
betterpath.egg-info/PKG-INFO
betterpath.egg-info/SOURCES.txt
betterpath.egg-info/dependency_links.txt
betterpath.egg-info/requires.txt
betterpath.egg-info/top_level.txt
bp/__init__.py
bp/abstract.py
bp/errors.py
bp/filepath.py
bp/generic.py
bp/memory.py
bp/readonly.py
bp/util.py
bp/win32.py
bp/zippath.py
bp/tests/__init__.py
bp/tests/test_memory.py
bp/tests/test_paths.py
bp/tests/test_readonly.py
bp/tests/test_util.py
bp/tests/test_zippath.py