Metadata-Version: 1.0
Name: betterpath
Version: 0.2.1
Summary: Path manipulation library
Home-page: http://github.com/MostAwesomeDude/betterpath
Author: Corbin Simpson
Author-email: cds@corbinsimpson.com
License: MIT/X11
Platform: UNKNOWN
